datarails/__init__.py
datarails/contexts.py
datarails/runner.py
datarails/step.py
datarails/type_vars.py
datarails-0.3.3.dist-info/LICENSE
datarails-0.3.3.dist-info/METADATA
datarails-0.3.3.dist-info/WHEEL
datarails-0.3.3.dist-info/top_level.txt
datarails-0.3.3.dist-info/RECORD
