Metadata-Version: 2.1
Name: datarails
Version: 0.3.3
Summary: A simple lightweight library for Dataframe based ETL pipelines
Project-URL: homepage, https://github.com/JesseMaitland/datarails
Project-URL: documentation, https://jessemaitland.github.io/datarails/
Project-URL: changelog, https://github.com/JesseMaitland/datarails/blob/main/CHANGELOG.md
Requires-Python: >=3.8
License-File: LICENSE
Provides-Extra: dev
Requires-Dist: setuptools (==68.0.0) ; extra == 'dev'
Requires-Dist: build (==0.10.0) ; extra == 'dev'
Requires-Dist: python-semantic-release (==7.34.6) ; extra == 'dev'
Requires-Dist: pytest (==7.2.2) ; extra == 'dev'
Requires-Dist: black (==22.6.0) ; extra == 'dev'
Requires-Dist: isort (==5.12.0) ; extra == 'dev'
Provides-Extra: docs
Requires-Dist: mkdocs (==1.4.2) ; extra == 'docs'
Requires-Dist: mkdocstrings[python] (==0.20.0) ; extra == 'docs'
Requires-Dist: mkdocs-material (==9.1.3) ; extra == 'docs'
Requires-Dist: markdown-include (==0.8.1) ; extra == 'docs'
